quartet_masterdata/__init__.py
quartet_masterdata/admin.py
quartet_masterdata/apps.py
quartet_masterdata/db.py
quartet_masterdata/geolocation.py
quartet_masterdata/models.py
quartet_masterdata/parsing.py
quartet_masterdata/routers.py
quartet_masterdata/serializers.py
quartet_masterdata/urls.py
quartet_masterdata/views.py
quartet_masterdata/viewsets.py
quartet_masterdata/management/__init__.py
quartet_masterdata/management/commands/__init__.py
quartet_masterdata/management/commands/create_masterdata_groups.py
quartet_masterdata/management/commands/md_test_data.py
quartet_masterdata/migrations/0001_initial.py
quartet_masterdata/migrations/0002_auto_20180821_1148.py
quartet_masterdata/migrations/0003_auto_20190305_2241.py
quartet_masterdata/migrations/0004_tradeitem_serial_number_length.py
quartet_masterdata/migrations/0005_tradeitem_pack_count.py
quartet_masterdata/migrations/0006_auto_20190812_1630.py
quartet_masterdata/migrations/0007_tradeitem_package_uom.py
quartet_masterdata/migrations/0008_outboundmapping.py
quartet_masterdata/migrations/0009_auto_20200221_1039.py
quartet_masterdata/migrations/0010_alter_company_id_alter_companytype_id_and_more.py
quartet_masterdata/migrations/__init__.py
quartet_masterdata/static/css/quartet_masterdata.css
quartet_masterdata/static/js/quartet_masterdata.js
tests/__init__.py
tests/factories.py
tests/settings.py
tests/test_api.py
tests/test_models.py
tests/urls.py
quartet_masterdata-3.0.0.dist-info/AUTHORS.rst
quartet_masterdata-3.0.0.dist-info/LICENSE
quartet_masterdata-3.0.0.dist-info/METADATA
quartet_masterdata-3.0.0.dist-info/WHEEL
quartet_masterdata-3.0.0.dist-info/top_level.txt
quartet_masterdata-3.0.0.dist-info/RECORD
