Metadata-Version: 2.1
Name: quartet-masterdata
Version: 3.0.0
Summary: Models and APIs to support material, lot and location master data.
Home-page: https://gitlab.com/serial-lab/quartet_masterdata
Author: Rob Magee
Author-email: slab@serial-lab.com
License: GPLv3
Keywords: quartet_masterdata
Platform: UNKNOWN
Classifier: Development Status :: 5 - Production/Stable
Classifier: Intended Audience :: Healthcare Industry
Classifier: Intended Audience :: Manufacturing
Classifier: Intended Audience :: Developers
Classifier: Framework :: Django
Classifier: License :: OSI Approved :: GNU General Public License v3 (GPLv3)
Classifier: Natural Language :: English
Classifier: Programming Language :: Python :: 3.3
Classifier: Programming Language :: Python :: 3.4
Classifier: Programming Language :: Python :: 3.5
Classifier: Programming Language :: Python :: 3.6
